rdchiral/__init__.py
rdchiral/bonds.py
rdchiral/chiral.py
rdchiral/clean.py
rdchiral/initialization.py
rdchiral/main.py
rdchiral/template_extractor.py
rdchiral/utils.py
rdchiral/test/__init__.py
rdchiral-1.1.0.dist-info/LICENSE
rdchiral-1.1.0.dist-info/METADATA
rdchiral-1.1.0.dist-info/WHEEL
rdchiral-1.1.0.dist-info/top_level.txt
rdchiral-1.1.0.dist-info/RECORD
