Metadata-Version: 2.1
Name: rdchiral
Version: 1.1.0
Summary: Wrapper for RDKit's RunReactants to improve stereochemistry handling
Home-page: https://github.com/connorcoley/rdchiral/
Author: Connor Coley
Author-email: ccoley@mit.edu
License: UNKNOWN
Platform: UNKNOWN
Classifier: Programming Language :: Python :: 3
Classifier: License :: OSI Approved :: MIT License
Classifier: Operating System :: OS Independent
Requires-Python: >=3.5
